LICENSE.txt
MANIFEST.in
README.rst
setup.cfg
setup.py
mord/__init__.py
mord/multiclass.py
mord/regression_based.py
mord/threshold_based.py
mord/utils.py
mord.egg-info/PKG-INFO
mord.egg-info/SOURCES.txt
mord.egg-info/dependency_links.txt
mord.egg-info/top_level.txt
mord/datasets/__init__.py
mord/datasets/base.py
mord/datasets/data/copenhagen_housing_survey.csv
mord/datasets/descr/copenhagen_housing_survey.rst