Metadata-Version: 2.1
Name: mord
Version: 0.7
Summary: Ordinal regression models
Home-page: https://pypi.python.org/pypi/mord
Author: Fabian Pedregosa
Author-email: f@bianp.net
License: UNKNOWN
Platform: UNKNOWN
Requires: numpy
Requires: scipy
Requires: sklearn
License-File: LICENSE.txt
